{
  "name": "MineHub",
  "colors": {
    "light": {
      "brand": "#463BE6"
    },
    "dark": {
      "brand": "#8982EB"
    }
  },
  "navigation": {
    "tabs": [
      {
        "tab": "Documentation",
        "icon": "book",
        "groups": [
          {
            "group": "Getting Started",
            "icon": "rocket",
            "pages": [
              {
                "title": "Introduction",
                "path": "introduction",
                "icon": "home"
              },
              {
                "title": "Trade lifecycle walkthrough - End to end",
                "path": "trade-lifecycle-walktrough---end-to-end"
              },
              {
                "title": "Features",
                "path": "features"
              }
            ]
          },
          {
            "group": "Main concepts",
            "icon": "layers",
            "pages": [
              {
                "title": "Allocations & Buy-Sell matching",
                "path": "allocations-buy-sell-matching"
              },
              {
                "title": "Local vs International markets",
                "path": "local-vs-international-markets"
              },
              {
                "title": "Pricing, Index & Offers",
                "path": "pricing-index-offers"
              },
              {
                "title": "Qualities, Commodities & Materials",
                "path": "qualities-commodities-materials"
              },
              {
                "title": "Users, Roles & Permissions",
                "path": "users-roles-permissions"
              },
              {
                "title": "Configuration & Settings",
                "path": "configuration-settings"
              },
              {
                "title": "Contract pricing",
                "path": "contract-pricing"
              }
            ]
          },
          {
            "group": "Modules",
            "icon": "compass",
            "pages": [
              {
                "title": "Companies, Sites & Contacts",
                "path": "companies-sites-contacts"
              },
              {
                "title": "Operations lifecycle",
                "path": "operations-lifecycle"
              },
              {
                "title": "Allocations",
                "path": "allocations-en"
              },
              {
                "title": "Budget",
                "path": "budget"
              },
              {
                "title": "Bookings",
                "path": "bookings-en"
              },
              {
                "title": "Logistics & Freight",
                "path": "logistics-freight"
              },
              {
                "title": "Containers",
                "path": "containers-en"
              },
              {
                "title": "Shipments",
                "path": "shipments-en"
              },
              {
                "title": "Margin",
                "path": "margin"
              },
              {
                "title": "Hedging",
                "path": "hedging"
              },
              {
                "title": "Charterparty & Cargo Bulk",
                "path": "charterparty-cargo-bulk-en"
              },
              {
                "title": "Documents, PDFs & Integrations",
                "path": "documents-pdfs-integrations"
              },
              {
                "title": "Tasks, Notes & Notifications",
                "path": "tasks-notes"
              },
              {
                "title": "Invoicing & Billing",
                "path": "invoicing-billing"
              }
            ]
          },
          {
            "group": "Workflows",
            "icon": "git-branch",
            "pages": [
              {
                "title": "Yard Reception (Local)",
                "path": "workflow-yard-reception-local-en"
              },
              {
                "title": "Index-Based Pricing",
                "path": "workflow-index-based-pricing-en"
              },
              {
                "title": "Debit & Credit Note",
                "path": "workflow-debit-credit-note-en"
              },
              {
                "title": "Month-End Margin Close",
                "path": "workflow-month-end-margin-close-en"
              },
              {
                "title": "Onboarding Supplier",
                "path": "workflow-onboarding-supplier-en"
              }
            ]
          }
        ]
      },
      {
        "tab": "API Reference",
        "icon": "code",
        "groups": [
          {
            "group": "Endpoints",
            "openapi": "api-reference/openapi.yaml"
          }
        ]
      },
      {
        "tab": "Help Center",
        "icon": "help-circle",
        "pages": [
          {
            "title": "Help Center",
            "path": "help-center",
            "icon": "home"
          },
          {
            "group": "FAQs",
            "icon": "help-circle",
            "expandable": false,
            "pages": [
              {
                "title": "How to Create a Project",
                "path": "help-center/faq/how-to-create-project"
              }
            ]
          },
          {
            "group": "Troubleshooting",
            "icon": "alert-triangle",
            "expandable": false,
            "pages": [
              {
                "title": "Cannot Invite Members",
                "path": "help-center/troubleshooting/cannot-invite-members"
              }
            ]
          },
          {
            "group": "Guides",
            "icon": "book-open",
            "expandable": false,
            "pages": [
              {
                "title": "Add Docs to Project",
                "path": "help-center/guides/add-docs-to-project"
              }
            ]
          }
        ]
      },
      {
        "tab": "Changelog",
        "icon": "clock",
        "pages": [
          {
            "title": "Release History",
            "path": "changelog",
            "icon": "history"
          }
        ]
      },
      {
        "tab": "Internal Troubleshooting",
        "pages": [],
        "icon": "flag"
      }
    ]
  }
}